tests/setup/__init__.py
tests/setup/service.py
verificac19/__init__.py
verificac19/exceptions.py
verificac19/verifier.py
verificac19/service/__init__.py
verificac19/service/_cache.py
verificac19/service/_settings.py
verificac19/service/service.py
verificac19/service/crl/__init__.py
verificac19/service/crl/_crl.py
verificac19/service/crl/check.py
verificac19/service/crl/chunk.py
verificac19/service/crl/download.py
verificac19/service/crl/mongo.py
verificac19/service/crl/uvcis.py
verificac19-1.2.0.dist-info/LICENSE
verificac19-1.2.0.dist-info/METADATA
verificac19-1.2.0.dist-info/WHEEL
verificac19-1.2.0.dist-info/top_level.txt
verificac19-1.2.0.dist-info/RECORD
