Metadata-Version: 2.1
Name: verificac19
Version: 1.2.0
Summary: VerificaC19 SDK for Python
Home-page: https://github.com/lotrekagency/pyverificac19
Author: Lotrèk Digital Agency
Author-email: dimmitutto@lotrek.it
License: MIT
Keywords: c19
Platform: UNKNOWN
Classifier: Intended Audience :: Developers
Classifier: Programming Language :: Python
Classifier: Programming Language :: Python :: 3
Requires-Python: >=3.7.*
License-File: LICENSE
Requires-Dist: requests (==2.26.0)
Requires-Dist: pymongo (==4.0.1)
Requires-Dist: dcc-utils (==0.2.1)
Requires-Dist: pyOpenSSL (==21.0.0)
